setup.py
rpi_featureSelection_matlab_tools/IPCMBSelector.py
rpi_featureSelection_matlab_tools/JMISelector.py
rpi_featureSelection_matlab_tools/STMBPlusSelector.py
rpi_featureSelection_matlab_tools/STMBSelector.py
rpi_featureSelection_matlab_tools/__init__.py
rpi_featureSelection_matlab_tools/rpi_featureSelection_matlab_tools.ctf
rpi_featureSelection_matlab_tools.egg-info/PKG-INFO
rpi_featureSelection_matlab_tools.egg-info/SOURCES.txt
rpi_featureSelection_matlab_tools.egg-info/dependency_links.txt
rpi_featureSelection_matlab_tools.egg-info/entry_points.txt
rpi_featureSelection_matlab_tools.egg-info/top_level.txt